<?xml version="1.0" encoding="UTF-8"?>

<power name="gashadokuro" type="tempunit" techname="Gashadokuro">
	<activetime>-1</activetime>
	<placement forceonmap="1" losprotounit="Gashadokuro">all</placement>
	<createunit quantity="1" radius="5.0" delay="0.0" norotate="">Gashadokuro</createunit>
	<soundset type="StartSound" listenertype="AllExceptCaster">GodPowerStart</soundset>
	<icon>god power nidhogg icon</icon>
	<usedicon>god power nidhogg icon done</usedicon>

	<recharges>0</recharges>
	<rechargetime>45 </rechargetime>
</power>
